{
  "Latlng": {
    "original_size": 26,
    "resolution": "high",
    "series_type": "distance",
    "data": [
      [
        51.298386,
        -0.72557
      ],
      [
        51.298386,
        -0.72557
      ],
      [
        51.298405,
        -0.726447
      ],
      [
        51.29833,
        -0.727175
      ],
      [
        51.298267,
        -0.72804
      ],
      [
        51.29827,
        -0.728264
      ],
      [
        51.29877,
        -0.728689
      ],
      [
        51.29932,
        -0.728712
      ],
      [
        51.299572,
        -0.728773
      ],
      [
        51.299606,
        -0.728816
      ],
      [
        51.30016,
        -0.728758
      ],
      [
        51.300667,
        -0.728443
      ],
      [
        51.301006,
        -0.728109
      ],
      [
        51.30149,
        -0.727674
      ],
      [
        51.302,
        -0.727346
      ],
      [
        51.302486,
        -0.727708
      ],
      [
        51.30293,
        -0.728172
      ],
      [
        51.303326,
        -0.728413
      ],
      [
        51.303864,
        -0.728751
      ],
      [
        51.304222,
        -0.728918
      ],
      [
        51.304344,
        -0.728999
      ],
      [
        51.304882,
        -0.72931
      ],
      [
        51.305164,
        -0.729475
      ],
      [
        51.305695,
        -0.729644
      ],
      [
        51.305878,
        -0.729767
      ],
      [
        51.305874,
        -0.729786
      ]
    ]
  },
  "Name": "Morning Ride",
  "ActivityType": "Ride",
  "StartDateTime": "2017-06-17T08:43:33Z"
}