{
  "Latlng": {
    "original_size": 284,
    "resolution": "high",
    "series_type": "distance",
    "data": [
      [
        51.305153,
        -0.72946
      ],
      [
        51.30504,
        -0.72939
      ],
      [
        51.304516,
        -0.729017
      ],
      [
        51.304253,
        -0.72861
      ],
      [
        51.304333,
        -0.728704
      ],
      [
        51.30424,
        -0.728796
      ],
      [
        51.304207,
        -0.728773
      ],
      [
        51.304203,
        -0.728786
      ],
      [
        51.30422,
        -0.7288
      ],
      [
        51.30429,
        -0.728766
      ],
      [
        51.304356,
        -0.728652
      ],
      [
        51.304504,
        -0.72781
      ],
      [
        51.304565,
        -0.727401
      ],
      [
        51.304653,
        -0.726538
      ],
      [
        51.304794,
        -0.725697
      ],
      [
        51.304626,
        -0.724919
      ],
      [
        51.30489,
        -0.724131
      ],
      [
        51.30499,
        -0.723961
      ],
      [
        51.305016,
        -0.723983
      ],
      [
        51.305096,
        -0.723999
      ],
      [
        51.305096,
        -0.724068
      ],
      [
        51.30499,
        -0.724029
      ],
      [
        51.30494,
        -0.724081
      ],
      [
        51.30461,
        -0.72483
      ],
      [
        51.30459,
        -0.724994
      ],
      [
        51.30471,
        -0.725824
      ],
      [
        51.304615,
        -0.726691
      ],
      [
        51.30459,
        -0.727036
      ],
      [
        51.3045,
        -0.727932
      ],
      [
        51.30436,
        -0.728802
      ],
      [
        51.304276,
        -0.728909
      ],
      [
        51.303734,
        -0.728679
      ],
      [
        51.3032,
        -0.728342
      ],
      [
        51.30278,
        -0.728004
      ],
      [
        51.302345,
        -0.727485
      ],
      [
        51.30189,
        -0.727019
      ],
      [
        51.30142,
        -0.726469
      ],
      [
        51.300945,
        -0.725984
      ],
      [
        51.300495,
        -0.725452
      ],
      [
        51.300182,
        -0.72507
      ],
      [
        51.30011,
        -0.724854
      ],
      [
        51.299984,
        -0.724006
      ],
      [
        51.299885,
        -0.723129
      ],
      [
        51.299793,
        -0.722363
      ],
      [
        51.299774,
        -0.722225
      ],
      [
        51.299603,
        -0.721379
      ],
      [
        51.29945,
        -0.720533
      ],
      [
        51.299263,
        -0.719711
      ],
      [
        51.299095,
        -0.718857
      ],
      [
        51.298904,
        -0.71804
      ],
      [
        51.298744,
        -0.717217
      ],
      [
        51.29866,
        -0.716532
      ],
      [
        51.29842,
        -0.715757
      ],
      [
        51.29819,
        -0.714974
      ],
      [
        51.297905,
        -0.714231
      ],
      [
        51.29764,
        -0.713473
      ],
      [
        51.297302,
        -0.712745
      ],
      [
        51.297012,
        -0.711963
      ],
      [
        51.296715,
        -0.711243
      ],
      [
        51.2964,
        -0.710491
      ],
      [
        51.29611,
        -0.709758
      ],
      [
        51.29583,
        -0.708991
      ],
      [
        51.29555,
        -0.708211
      ],
      [
        51.29527,
        -0.707445
      ],
      [
        51.294933,
        -0.706721
      ],
      [
        51.29458,
        -0.706055
      ],
      [
        51.294342,
        -0.705562
      ],
      [
        51.294373,
        -0.705559
      ],
      [
        51.294426,
        -0.705435
      ],
      [
        51.29444,
        -0.705433
      ],
      [
        51.29493,
        -0.70513
      ],
      [
        51.295315,
        -0.704527
      ],
      [
        51.29574,
        -0.704381
      ],
      [
        51.29594,
        -0.703918
      ],
      [
        51.295906,
        -0.703872
      ],
      [
        51.29574,
        -0.704039
      ],
      [
        51.29571,
        -0.703982
      ],
      [
        51.295597,
        -0.70405
      ],
      [
        51.29553,
        -0.70409
      ],
      [
        51.295513,
        -0.704073
      ],
      [
        51.2955,
        -0.703947
      ],
      [
        51.29552,
        -0.703924
      ],
      [
        51.295536,
        -0.703911
      ],
      [
        51.295887,
        -0.703267
      ],
      [
        51.296196,
        -0.702534
      ],
      [
        51.296654,
        -0.70203
      ],
      [
        51.29693,
        -0.701373
      ],
      [
        51.296955,
        -0.700504
      ],
      [
        51.296787,
        -0.700304
      ],
      [
        51.29672,
        -0.700279
      ],
      [
        51.29641,
        -0.700103
      ],
      [
        51.296387,
        -0.700084
      ],
      [
        51.2963,
        -0.700032
      ],
      [
        51.296238,
        -0.699939
      ],
      [
        51.295864,
        -0.699301
      ],
      [
        51.295727,
        -0.69905
      ],
      [
        51.29565,
        -0.698995
      ],
      [
        51.295246,
        -0.69881
      ],
      [
        51.295067,
        -0.698759
      ],
      [
        51.29502,
        -0.698775
      ],
      [
        51.294502,
        -0.699
      ],
      [
        51.294006,
        -0.698706
      ],
      [
        51.294098,
        -0.697934
      ],
      [
        51.294178,
        -0.697841
      ],
      [
        51.29414,
        -0.698333
      ],
      [
        51.294586,
        -0.697843
      ],
      [
        51.294746,
        -0.696986
      ],
      [
        51.294857,
        -0.696837
      ],
      [
        51.29539,
        -0.696771
      ],
      [
        51.295536,
        -0.696648
      ],
      [
        51.29572,
        -0.696604
      ],
      [
        51.295803,
        -0.69657
      ],
      [
        51.29607,
        -0.696359
      ],
      [
        51.295616,
        -0.696701
      ],
      [
        51.295666,
        -0.696696
      ],
      [
        51.295692,
        -0.696641
      ],
      [
        51.29572,
        -0.696571
      ],
      [
        51.295635,
        -0.696551
      ],
      [
        51.295555,
        -0.696691
      ],
      [
        51.295734,
        -0.696642
      ],
      [
        51.29577,
        -0.696645
      ],
      [
        51.295845,
        -0.696631
      ],
      [
        51.29627,
        -0.696069
      ],
      [
        51.296146,
        -0.695277
      ],
      [
        51.29598,
        -0.694873
      ],
      [
        51.295673,
        -0.694135
      ],
      [
        51.29529,
        -0.693521
      ],
      [
        51.29487,
        -0.692969
      ],
      [
        51.294514,
        -0.692309
      ],
      [
        51.29458,
        -0.692147
      ],
      [
        51.294987,
        -0.691608
      ],
      [
        51.2951,
        -0.69149
      ],
      [
        51.29547,
        -0.69087
      ],
      [
        51.29545,
        -0.690665
      ],
      [
        51.29557,
        -0.689897
      ],
      [
        51.295654,
        -0.689755
      ],
      [
        51.295776,
        -0.689212
      ],
      [
        51.29592,
        -0.689573
      ],
      [
        51.295967,
        -0.689489
      ],
      [
        51.296104,
        -0.689551
      ],
      [
        51.296127,
        -0.689512
      ],
      [
        51.29613,
        -0.689363
      ],
      [
        51.296173,
        -0.689292
      ],
      [
        51.296253,
        -0.689292
      ],
      [
        51.29627,
        -0.689241
      ],
      [
        51.296448,
        -0.688854
      ],
      [
        51.29647,
        -0.688867
      ],
      [
        51.296513,
        -0.688815
      ],
      [
        51.296566,
        -0.688594
      ],
      [
        51.296886,
        -0.688043
      ],
      [
        51.297157,
        -0.688073
      ],
      [
        51.297253,
        -0.688027
      ],
      [
        51.297283,
        -0.687912
      ],
      [
        51.297344,
        -0.687503
      ],
      [
        51.297318,
        -0.687329
      ],
      [
        51.29722,
        -0.687127
      ],
      [
        51.296803,
        -0.686971
      ],
      [
        51.296623,
        -0.68682
      ],
      [
        51.29628,
        -0.686674
      ],
      [
        51.29626,
        -0.686639
      ],
      [
        51.296257,
        -0.686584
      ],
      [
        51.296307,
        -0.686338
      ],
      [
        51.296352,
        -0.68555
      ],
      [
        51.29652,
        -0.685787
      ],
      [
        51.296585,
        -0.685722
      ],
      [
        51.29682,
        -0.68496
      ],
      [
        51.296867,
        -0.684647
      ],
      [
        51.29703,
        -0.684506
      ],
      [
        51.297016,
        -0.684339
      ],
      [
        51.2969,
        -0.684235
      ],
      [
        51.29669,
        -0.684379
      ],
      [
        51.296505,
        -0.684349
      ],
      [
        51.296432,
        -0.684222
      ],
      [
        51.296364,
        -0.684046
      ],
      [
        51.295864,
        -0.684067
      ],
      [
        51.295475,
        -0.684698
      ],
      [
        51.295113,
        -0.685368
      ],
      [
        51.29479,
        -0.686077
      ],
      [
        51.29444,
        -0.686734
      ],
      [
        51.2941,
        -0.687444
      ],
      [
        51.293804,
        -0.688215
      ],
      [
        51.293663,
        -0.689041
      ],
      [
        51.293705,
        -0.689476
      ],
      [
        51.293663,
        -0.689486
      ],
      [
        51.29325,
        -0.690025
      ],
      [
        51.292816,
        -0.690558
      ],
      [
        51.292538,
        -0.691134
      ],
      [
        51.292618,
        -0.691483
      ],
      [
        51.29218,
        -0.69199
      ],
      [
        51.292152,
        -0.692042
      ],
      [
        51.292095,
        -0.691915
      ],
      [
        51.29261,
        -0.691517
      ],
      [
        51.293015,
        -0.691264
      ],
      [
        51.29304,
        -0.691237
      ],
      [
        51.293068,
        -0.691256
      ],
      [
        51.292904,
        -0.691351
      ],
      [
        51.29329,
        -0.690726
      ],
      [
        51.29329,
        -0.690683
      ],
      [
        51.293198,
        -0.690435
      ],
      [
        51.293224,
        -0.690405
      ],
      [
        51.293365,
        -0.690528
      ],
      [
        51.293392,
        -0.690586
      ],
      [
        51.29343,
        -0.690722
      ],
      [
        51.293385,
        -0.690712
      ],
      [
        51.2933,
        -0.690673
      ],
      [
        51.293392,
        -0.690664
      ],
      [
        51.293377,
        -0.690627
      ],
      [
        51.293194,
        -0.690345
      ],
      [
        51.29321,
        -0.690343
      ],
      [
        51.293274,
        -0.690424
      ],
      [
        51.29338,
        -0.690425
      ],
      [
        51.293423,
        -0.690406
      ],
      [
        51.293507,
        -0.690497
      ],
      [
        51.293777,
        -0.690818
      ],
      [
        51.293854,
        -0.690827
      ],
      [
        51.29396,
        -0.690632
      ],
      [
        51.293976,
        -0.690659
      ],
      [
        51.294167,
        -0.69147
      ],
      [
        51.294464,
        -0.692184
      ],
      [
        51.294827,
        -0.692853
      ],
      [
        51.295258,
        -0.693407
      ],
      [
        51.295315,
        -0.693573
      ],
      [
        51.295086,
        -0.694377
      ],
      [
        51.294827,
        -0.69518
      ],
      [
        51.294544,
        -0.695953
      ],
      [
        51.29433,
        -0.696768
      ],
      [
        51.29412,
        -0.697566
      ],
      [
        51.294113,
        -0.697843
      ],
      [
        51.294098,
        -0.697819
      ],
      [
        51.29408,
        -0.697859
      ],
      [
        51.293747,
        -0.698267
      ],
      [
        51.294098,
        -0.698903
      ],
      [
        51.294636,
        -0.698881
      ],
      [
        51.295155,
        -0.69875
      ],
      [
        51.295677,
        -0.698988
      ],
      [
        51.295925,
        -0.699761
      ],
      [
        51.295685,
        -0.700528
      ],
      [
        51.295452,
        -0.701066
      ],
      [
        51.29504,
        -0.701709
      ],
      [
        51.294746,
        -0.702429
      ],
      [
        51.294598,
        -0.703294
      ],
      [
        51.29443,
        -0.704154
      ],
      [
        51.294266,
        -0.705003
      ],
      [
        51.29448,
        -0.705708
      ],
      [
        51.294785,
        -0.706452
      ],
      [
        51.295055,
        -0.707226
      ],
      [
        51.295383,
        -0.707931
      ],
      [
        51.295708,
        -0.708656
      ],
      [
        51.29599,
        -0.709438
      ],
      [
        51.296284,
        -0.710188
      ],
      [
        51.296555,
        -0.710948
      ],
      [
        51.29683,
        -0.71173
      ],
      [
        51.297123,
        -0.712466
      ],
      [
        51.297413,
        -0.713242
      ],
      [
        51.297707,
        -0.714006
      ],
      [
        51.298004,
        -0.714779
      ],
      [
        51.29833,
        -0.715519
      ],
      [
        51.298386,
        -0.715733
      ],
      [
        51.298443,
        -0.71623
      ],
      [
        51.298542,
        -0.716939
      ],
      [
        51.298714,
        -0.717875
      ],
      [
        51.29889,
        -0.718762
      ],
      [
        51.299084,
        -0.719574
      ],
      [
        51.299313,
        -0.720547
      ],
      [
        51.299507,
        -0.721473
      ],
      [
        51.299725,
        -0.722354
      ],
      [
        51.299904,
        -0.723238
      ],
      [
        51.300007,
        -0.724104
      ],
      [
        51.300095,
        -0.724989
      ],
      [
        51.300102,
        -0.725051
      ],
      [
        51.30052,
        -0.725592
      ],
      [
        51.300884,
        -0.726015
      ],
      [
        51.30137,
        -0.726468
      ],
      [
        51.301838,
        -0.726972
      ],
      [
        51.30193,
        -0.727342
      ],
      [
        51.302452,
        -0.727673
      ],
      [
        51.30289,
        -0.728202
      ],
      [
        51.303394,
        -0.728538
      ],
      [
        51.303917,
        -0.728855
      ],
      [
        51.304226,
        -0.728955
      ],
      [
        51.30473,
        -0.72927
      ],
      [
        51.305042,
        -0.729532
      ],
      [
        51.305595,
        -0.729637
      ],
      [
        51.30582,
        -0.729787
      ]
    ]
  },
  "Name": "11km - Tunnel Hill with Ben and the Turners",
  "ActivityType": "Ride",
  "StartDateTime": "2018-08-13T18:04:10Z"
}